Laboratorios/Laboratorio 2/alu_riscv.v
module alu_riscv (
    input [31:0] a, b,
    input [9:0] ctrl, // Vector de 10 bits: {add, sub, sll, slt, sltu, xor, srl, sra, or, and}
    output reg [31:0] out
);
    always @(*) begin
        case (ctrl)
            10'b1000000000: out = a + b;         // add
            10'b0100000000: out = a - b;         // sub
            10'b0010000000: out = a << b[4:0];   // sll
            10'b0001000000: out = ($signed(a) < $signed(b)) ? 32'b1 : 32'b0; // slt
            10'b0000100000: out = (a < b) ? 32'b1 : 32'b0; // sltu
            10'b0000010000: out = a ^ b;         // xor
            10'b0000001000: out = a >> b[4:0];   // srl
            10'b0000000100: out = $signed(a) >>> b[4:0]; // sra
            10'b0000000010: out = a | b;         // or
            10'b0000000001: out = a & b;         // and
            default:        out = 32'b0;
        endcase
    end
endmodule

Laboratorios/Laboratorio 5/register_file.v
module register_file (
    input  wire        clk,            // Señal de reloj
    input  wire        wr_en,          // Habilitador de escritura
    input  wire [4:0]  wr_index,       // Dirección de escritura
    input  wire [31:0] wr_data,        // Dato a escribir
    input  wire [4:0]  rd_index1,      // Dirección de lectura 1
    input  wire [4:0]  rd_index2,      // Dirección de lectura 2
    output wire [31:0] rd_data1,       // Dato leído 1
    output wire [31:0] rd_data2        // Dato leído 2
);

    // Memoria de 32 registros de 32 bits
    reg [31:0] mem [31:0];

    integer i;

    // Inicialización opcional (útil para simulación)
    initial begin
        for (i = 0; i < 32; i = i + 1)
            mem[i] = 32'd0;
    end

    // Escritura sincrónica
    always @(posedge clk) begin
        if (wr_en && (wr_index != 5'd0)) begin
            mem[wr_index] <= wr_data;
        end
    end

    // Lecturas combinacionales
    assign rd_data1 = (rd_index1 == 5'd0) ? 32'd0 : mem[rd_index1];
    assign rd_data2 = (rd_index2 == 5'd0) ? 32'd0 : mem[rd_index2];

endmodule

Laboratorios/Laboratorio 3/my_riscv.v
module my_riscv (
    input clk,          // Reloj del procesador
    input rst,          // Reset del procesador
    input [31:0] instr,  // Instrucción de entrada
    output [31:0] iaddr,

    output [31:0] daddr,
    input [31:0] ddata_in,
    output [31:0] ddata_out,
    output dwr_en,
    output drd_en
);

    // Contador de programa
    reg [31:0] pc;
    assign iaddr = pc;  // Conecta el PC al bus de direcciones de la IMEM
    wire [31:0] next_pc;
        

    // Contador en anillo que lleva el registro del estado dentro del ciclo de ejecución
    reg state_fetch, state_decode, state_execute;
    
    always @(negedge clk) begin
        if (rst) begin
            state_fetch <= 1;
            state_decode <= 0;
            state_execute <= 0;
        end else begin
            state_fetch <= state_execute;
            state_decode <= state_fetch;
            state_execute <= state_decode;
        end
    end

    reg [31:0] IR;      // Registro de instrucción
    
    // PC se inicializa en reset; la lógica de avance se agregará más adelante
    always @(posedge clk) begin
        if (rst)
            pc <= 32'h0;
        else if (state_execute)
            pc <= next_pc;
    end

    always @(posedge clk) begin
        if (rst)
            IR <= 32'd0;
        else if (state_fetch)
            IR <= instr;
    end

    // --- Extracción de los campos del registro de instrucción (IR) ---
    wire [6:0] funct7;
    wire [4:0] rs2;
    wire [4:0] rs1;
    wire [2:0] funct3;
    wire [4:0] rd;
    wire [6:0] opcode;

    assign funct7 = IR[31:25];
    assign rs2    = IR[24:20];
    assign rs1    = IR[19:15];
    assign funct3 = IR[14:12];
    assign rd     = IR[11:7];
    assign opcode = IR[6:0];

    // --- Salidas del Register File (RF) ---
    wire [31:0] src1_value;
    wire [31:0] src2_value;

    // --- Operandos de entrada a la ALU ---
    wire [31:0] alu_a;
    wire [31:0] alu_b;

    // --- Salida de la ALU ---
    wire [31:0] alu_out;

    // --- Señales de control de la unidad de control (CU) ---
    wire wr_en;
    wire [10:0] dec_bits;
    wire is_add, is_sub, is_sll, is_slt, is_sltu, is_xor, is_srl, is_sra, is_or, is_and;

    // Nuevas señales para tipos de instrucción
    wire is_r_instr;
    wire is_i_instr;
    wire is_s_instr;
    wire is_b_instr;
    wire is_u_instr;
    wire is_j_instr;
    wire is_valid; //---------------------------------------------------------------------

    // señales de salto condicional individuales
    wire is_beq, is_bne, is_blt, is_bge, is_bltu, is_bgeu;

    // --- Instanciación del Register File (RF) ---
  register_file rv_rf (
    .clk(clk),
    // solo habilitamos escritura durante el ciclo de ejecución
    .wr_en(wr_en & state_execute),
    .wr_index(rd),
    .wr_data(alu_out),
    .rd_index1(rs1),
    .rd_data1(src1_value),
    .rd_index2(rs2),
    .rd_data2(src2_value)
 );

    // --- Generación del valor Inmediato (IMM) y extensión de signo ---
    // 
    wire [31:0] imm;
    assign imm = is_i_instr ? { {21{IR[31]}}, IR[30:20] } :
                 is_s_instr ? { {21{IR[31]}}, IR[30:25], IR[11:7] } :
                 is_b_instr ? { {20{IR[31]}}, IR[7], IR[30:25], IR[11:8], 1'b0 } :
                 is_u_instr ? { IR[31:12], 12'b0 } :
                 is_j_instr ? { {12{IR[31]}}, IR[19:12], IR[20], IR[30:21], 1'b0 } :
                 32'b0;

    wire imm_valid = is_i_instr | is_s_instr | is_b_instr | is_u_instr | is_j_instr;

    // --- comparador para saltos condicionales ---
    // usamos valores firmados para blt/bge, sin signo para bltu/bgeu
    wire signed [31:0] s1 = src1_value;
    wire signed [31:0] s2 = src2_value;
    wire taken_br;

    assign taken_br = (is_beq  && (src1_value == src2_value)) |
                      (is_bne  && (src1_value != src2_value)) |
                      (is_blt  && (s1 < s2)) |
                      (is_bge  && (s1 >= s2)) |
                      (is_bltu && (src1_value < src2_value)) |
                      (is_bgeu && (src1_value >= src2_value));

    // cálculo de valores para siguiente PC
    wire [31:0] pc_plus_4  = pc + 32'd4;
    wire [31:0] br_tgt_pc  = pc + imm;        // PC relativo + immediate
    assign next_pc    = (is_j_instr || taken_br) ? br_tgt_pc : pc_plus_4;

    // --- MUX para la entrada B de la ALU ---
    assign alu_a = src1_value;
    assign alu_b = (is_r_instr) ? src2_value : imm; // Si no es tipo R, usa el inmediato

    // --- Instanciación de la ALU ---
    alu_riscv rv_alu (
        .a(alu_a),
        .b(alu_b),
        .out(alu_out),
        // Aquí unimos las señales de tipo R con sus versiones inmediatas (tipo I)
        .ctrl({
            is_add | is_addi, 
            is_sub, 
            is_sll | is_slli, 
            is_slt | is_slti, 
            is_sltu| is_sltui, 
            is_xor | is_xori, 
            is_srl | is_srli, 
            is_sra | is_srai, 
            is_or  | is_ori, 
            is_and | is_andi
        })
    );

    // actualización del PC en etapa execute
    always @(posedge clk) begin
        if (rst) begin
            pc <= 32'h0;
        end else if (state_execute) begin
            pc <= next_pc;
        end
    end

    // --- Unidad de Control (CU) ---
    assign is_valid = (opcode[1:0] == 2'b11);
    
    // Identificación de Tipos
    assign is_r_instr = (opcode[6:2] == 5'b01100);
    assign is_i_instr = (opcode[6:2] == 5'b00000) || (opcode[6:2] == 5'b00100) || (opcode[6:2] == 5'b11001);
    assign is_s_instr = (opcode[6:2] == 5'b01000);
    assign is_b_instr = (opcode[6:2] == 5'b11000);
    assign is_u_instr = (opcode[6:2] == 5'b00101) || (opcode[6:2] == 5'b01101);
    assign is_j_instr = (opcode[6:2] == 5'b11011);

    assign wr_en = (is_r_instr | is_i_instr | is_u_instr | is_j_instr) & is_valid;

    // señales para cada tipo de rama (usar funct3)
    assign is_beq  = is_b_instr && (funct3 == 3'b000);
    assign is_bne  = is_b_instr && (funct3 == 3'b001);
    assign is_blt  = is_b_instr && (funct3 == 3'b100);
    assign is_bge  = is_b_instr && (funct3 == 3'b101);
    assign is_bltu = is_b_instr && (funct3 == 3'b110);
    assign is_bgeu = is_b_instr && (funct3 == 3'b111);


    // Decodificación de instrucciones Tipo R
    assign dec_bits = {funct7[5], funct3, opcode};
    assign is_add  = (dec_bits == 11'b0_000_0110011);
    assign is_sub  = (dec_bits == 11'b1_000_0110011);
    assign is_sll  = (dec_bits == 11'b0_001_0110011);
    assign is_slt  = (dec_bits == 11'b0_010_0110011);
    assign is_sltu = (dec_bits == 11'b0_011_0110011);
    assign is_xor  = (dec_bits == 11'b0_100_0110011);
    assign is_srl  = (dec_bits == 11'b0_101_0110011);
    assign is_sra  = (dec_bits == 11'b1_101_0110011);
    assign is_or   = (dec_bits == 11'b0_110_0110011);
    assign is_and  = (dec_bits == 11'b0_111_0110011);

    // Decodificación de instrucciones Tipo I (Opcodes inmediatos 00100)
    // Para las tipo I, funct7 no existe, solo usamos funct3 y opcode
    wire [9:0] dec_bits_i = {funct3, opcode};
    assign is_addi  = (dec_bits_i == 10'b000_0010011);
    assign is_slti  = (dec_bits_i == 10'b010_0010011);
    assign is_sltui = (dec_bits_i == 10'b011_0010011);
    assign is_xori  = (dec_bits_i == 10'b100_0010011);
    assign is_ori   = (dec_bits_i == 10'b110_0010011);
    assign is_andi  = (dec_bits_i == 10'b111_0010011);
    
    // Casos especiales de tipo I: desplazamientos (usan parte de funct7)
    assign is_slli  = (dec_bits == 11'b0_001_0010011);
    assign is_srli  = (dec_bits == 11'b0_101_0010011);
    assign is_srai  = (dec_bits == 11'b1_101_0010011);

endmodule

Laboratorios/Laboratorio 3/tb_my_riscv.v
`timescale 1ns/1ps

module tb_riscv;
  
  // Señales de prueba
  reg  [31:0] instr;
  reg  clk;
  reg  rst;
  
  
  // Instancia del DUT (Device Under Test)
  my_riscv uut (
    .clk(clk),
    .instr(instr)
  );

  // Bloque inicial: aplica estímulos
  integer i;
  initial begin

    // Configurar la generación de archivos de volcado
    $dumpfile("tb_riscv.vcd");
    $dumpvars(0, tb_riscv);
	for(i=0; i<32; i=i+1) $dumpvars(0, uut.rv_rf.mem[i]);
    
    //Inicia el register file para facilitar la prueba
	//En este caso cada registro xN toma el valor de N, por ejemplo, x10 = 10.
    for(i=0; i<32; i=i+1) uut.rv_rf.mem[i] = i;
    
    // Muestra en consola los valores de interés cada vez que cambien
    $monitor($time, " clk=%d | ins=%h x4=%h x5=%h x6=%h", clk, instr, uut.rv_rf.mem[4], uut.rv_rf.mem[5], uut.rv_rf.mem[6]);

    #0;  clk = 0;
		 rst = 1;
	
    #3;  rst = 0; 
    	 instr = 32'b0000000_00010_00011_000_00100_0110011;  //add x4, x3, x2
    	 $display("add x4, x3, x2");
    
    #8;  instr = 32'b0100000_00010_00011_000_00101_0110011;  //sub x5, x3, x2 
    	 $display("sub x5, x3, x2");
    
    #8;  instr = 32'b0000000_01100_01010_111_00110_0110011;  //and x6, x10, x12  
    	 $display("and x6, x10, x12");

	#16;
    // Fin de la simulación
    $finish;
  end
  
  always
    begin
        #2 clk=!clk;
    end

endmodule

Laboratorios/Laboratorio 3/tb_riscv.vcd
$date
	Tue Mar  3 14:51:20 2026
$end
$version
	Icarus Verilog
$end
$timescale
	1ps
$end
$scope module tb_riscv $end
$var reg 1 ! clk $end
$var reg 32 " instr [31:0] $end
$var reg 1 # rst $end
$var integer 32 $ i [31:0] $end
$scope module uut $end
$var wire 32 % alu_a [31:0] $end
$var wire 1 ! clk $end
$var wire 32 & iaddr [31:0] $end
$var wire 1 ' imm_valid $end
$var wire 32 ( instr [31:0] $end
$var wire 1 ) is_beq $end
$var wire 1 * is_bge $end
$var wire 1 + is_bgeu $end
$var wire 1 , is_blt $end
$var wire 1 - is_bltu $end
$var wire 1 . is_bne $end
$var wire 1 / is_i_instr $end
$var wire 1 0 is_u_instr $end
$var wire 1 # rst $end
$var wire 32 1 s1 [31:0] $end
$var wire 32 2 s2 [31:0] $end
$var wire 1 3 taken_br $end
$var wire 1 4 wr_en $end
$var wire 32 5 src2_value [31:0] $end
$var wire 32 6 src1_value [31:0] $end
$var wire 5 7 rs2 [4:0] $end
$var wire 5 8 rs1 [4:0] $end
$var wire 5 9 rd [4:0] $end
$var wire 32 : pc_plus_4 [31:0] $end
$var wire 7 ; opcode [6:0] $end
$var wire 32 < next_pc [31:0] $end
$var wire 1 = is_xori $end
$var wire 1 > is_xor $end
$var wire 1 ? is_valid $end
$var wire 1 @ is_sub $end
$var wire 1 A is_srli $end
$var wire 1 B is_srl $end
$var wire 1 C is_srai $end
$var wire 1 D is_sra $end
$var wire 1 E is_sltui $end
$var wire 1 F is_sltu $end
$var wire 1 G is_slti $end
$var wire 1 H is_slt $end
$var wire 1 I is_slli $end
$var wire 1 J is_sll $end
$var wire 1 K is_s_instr $end
$var wire 1 L is_r_instr $end
$var wire 1 M is_ori $end
$var wire 1 N is_or $end
$var wire 1 O is_j_instr $end
$var wire 1 P is_b_instr $end
$var wire 1 Q is_andi $end
$var wire 1 R is_and $end
$var wire 1 S is_addi $end
$var wire 1 T is_add $end
$var wire 32 U imm [31:0] $end
$var wire 7 V funct7 [6:0] $end
$var wire 3 W funct3 [2:0] $end
$var wire 10 X dec_bits_i [9:0] $end
$var wire 11 Y dec_bits [10:0] $end
$var wire 32 Z br_tgt_pc [31:0] $end
$var wire 32 [ alu_out [31:0] $end
$var wire 32 \ alu_b [31:0] $end
$var reg 32 ] IR [31:0] $end
$var reg 32 ^ pc [31:0] $end
$var reg 1 _ state_decode $end
$var reg 1 ` state_execute $end
$var reg 1 a state_fetch $end
$scope module rv_alu $end
$var wire 32 b a [31:0] $end
$var wire 32 c b [31:0] $end
$var wire 10 d ctrl [9:0] $end
$var reg 32 e out [31:0] $end
$upscope $end
$scope module rv_rf $end
$var wire 1 ! clk $end
$var wire 5 f rd_index1 [4:0] $end
$var wire 5 g rd_index2 [4:0] $end
$var wire 32 h wr_data [31:0] $end
$var wire 1 i wr_en $end
$var wire 5 j wr_index [4:0] $end
$var wire 32 k rd_data2 [31:0] $end
$var wire 32 l rd_data1 [31:0] $end
$var integer 32 m i [31:0] $end
$upscope $end
$upscope $end
$upscope $end
$scope module tb_riscv $end
$scope module uut $end
$scope module rv_rf $end
$var reg 32 n \mem[0] [31:0] $end
$upscope $end
$upscope $end
$upscope $end
$scope module tb_riscv $end
$scope module uut $end
$scope module rv_rf $end
$var reg 32 o \mem[1] [31:0] $end
$upscope $end
$upscope $end
$upscope $end
$scope module tb_riscv $end
$scope module uut $end
$scope module rv_rf $end
$var reg 32 p \mem[2] [31:0] $end
$upscope $end
$upscope $end
$upscope $end
$scope module tb_riscv $end
$scope module uut $end
$scope module rv_rf $end
$var reg 32 q \mem[3] [31:0] $end
$upscope $end
$upscope $end
$upscope $end
$scope module tb_riscv $end
$scope module uut $end
$scope module rv_rf $end
$var reg 32 r \mem[4] [31:0] $end
$upscope $end
$upscope $end
$upscope $end
$scope module tb_riscv $end
$scope module uut $end
$scope module rv_rf $end
$var reg 32 s \mem[5] [31:0] $end
$upscope $end
$upscope $end
$upscope $end
$scope module tb_riscv $end
$scope module uut $end
$scope module rv_rf $end
$var reg 32 t \mem[6] [31:0] $end
$upscope $end
$upscope $end
$upscope $end
$scope module tb_riscv $end
$scope module uut $end
$scope module rv_rf $end
$var reg 32 u \mem[7] [31:0] $end
$upscope $end
$upscope $end
$upscope $end
$scope module tb_riscv $end
$scope module uut $end
$scope module rv_rf $end
$var reg 32 v \mem[8] [31:0] $end
$upscope $end
$upscope $end
$upscope $end
$scope module tb_riscv $end
$scope module uut $end
$scope module rv_rf $end
$var reg 32 w \mem[9] [31:0] $end
$upscope $end
$upscope $end
$upscope $end
$scope module tb_riscv $end
$scope module uut $end
$scope module rv_rf $end
$var reg 32 x \mem[10] [31:0] $end
$upscope $end
$upscope $end
$upscope $end
$scope module tb_riscv $end
$scope module uut $end
$scope module rv_rf $end
$var reg 32 y \mem[11] [31:0] $end
$upscope $end
$upscope $end
$upscope $end
$scope module tb_riscv $end
$scope module uut $end
$scope module rv_rf $end
$var reg 32 z \mem[12] [31:0] $end
$upscope $end
$upscope $end
$upscope $end
$scope module tb_riscv $end
$scope module uut $end
$scope module rv_rf $end
$var reg 32 { \mem[13] [31:0] $end
$upscope $end
$upscope $end
$upscope $end
$scope module tb_riscv $end
$scope module uut $end
$scope module rv_rf $end
$var reg 32 | \mem[14] [31:0] $end
$upscope $end
$upscope $end
$upscope $end
$scope module tb_riscv $end
$scope module uut $end
$scope module rv_rf $end
$var reg 32 } \mem[15] [31:0] $end
$upscope $end
$upscope $end
$upscope $end
$scope module tb_riscv $end
$scope module uut $end
$scope module rv_rf $end
$var reg 32 ~ \mem[16] [31:0] $end
$upscope $end
$upscope $end
$upscope $end
$scope module tb_riscv $end
$scope module uut $end
$scope module rv_rf $end
$var reg 32 !" \mem[17] [31:0] $end
$upscope $end
$upscope $end
$upscope $end
$scope module tb_riscv $end
$scope module uut $end
$scope module rv_rf $end
$var reg 32 "" \mem[18] [31:0] $end
$upscope $end
$upscope $end
$upscope $end
$scope module tb_riscv $end
$scope module uut $end
$scope module rv_rf $end
$var reg 32 #" \mem[19] [31:0] $end
$upscope $end
$upscope $end
$upscope $end
$scope module tb_riscv $end
$scope module uut $end
$scope module rv_rf $end
$var reg 32 $" \mem[20] [31:0] $end
$upscope $end
$upscope $end
$upscope $end
$scope module tb_riscv $end
$scope module uut $end
$scope module rv_rf $end
$var reg 32 %" \mem[21] [31:0] $end
$upscope $end
$upscope $end
$upscope $end
$scope module tb_riscv $end
$scope module uut $end
$scope module rv_rf $end
$var reg 32 &" \mem[22] [31:0] $end
$upscope $end
$upscope $end
$upscope $end
$scope module tb_riscv $end
$scope module uut $end
$scope module rv_rf $end
$var reg 32 '" \mem[23] [31:0] $end
$upscope $end
$upscope $end
$upscope $end
$scope module tb_riscv $end
$scope module uut $end
$scope module rv_rf $end
$var reg 32 (" \mem[24] [31:0] $end
$upscope $end
$upscope $end
$upscope $end
$scope module tb_riscv $end
$scope module uut $end
$scope module rv_rf $end
$var reg 32 )" \mem[25] [31:0] $end
$upscope $end
$upscope $end
$upscope $end
$scope module tb_riscv $end
$scope module uut $end
$scope module rv_rf $end
$var reg 32 *" \mem[26] [31:0] $end
$upscope $end
$upscope $end
$upscope $end
$scope module tb_riscv $end
$scope module uut $end
$scope module rv_rf $end
$var reg 32 +" \mem[27] [31:0] $end
$upscope $end
$upscope $end
$upscope $end
$scope module tb_riscv $end
$scope module uut $end
$scope module rv_rf $end
$var reg 32 ," \mem[28] [31:0] $end
$upscope $end
$upscope $end
$upscope $end
$scope module tb_riscv $end
$scope module uut $end
$scope module rv_rf $end
$var reg 32 -" \mem[29] [31:0] $end
$upscope $end
$upscope $end
$upscope $end
$scope module tb_riscv $end
$scope module uut $end
$scope module rv_rf $end
$var reg 32 ." \mem[30] [31:0] $end
$upscope $end
$upscope $end
$upscope $end
$scope module tb_riscv $end
$scope module uut $end
$scope module rv_rf $end
$var reg 32 /" \mem[31] [31:0] $end
$upscope $end
$upscope $end
$upscope $end
$enddefinitions $end
$comment Show the parameter values. $end
$dumpall
$end
#0
$dumpvars
b11111 /"
b11110 ."
b11101 -"
b11100 ,"
b11011 +"
b11010 *"
b11001 )"
b11000 ("
b10111 '"
b10110 &"
b10101 %"
b10100 $"
b10011 #"
b10010 ""
b10001 !"
b10000 ~
b1111 }
b1110 |
b1101 {
b1100 z
b1011 y
b1010 x
b1001 w
b1000 v
b111 u
b110 t
b101 s
b100 r
b11 q
b10 p
b1 o
b0 n
b100000 m
bx l
bx k
bx j
0i
bx h
bx g
bx f
bx e
bx d
bx c
bx b
1a
0`
0_
bx ^
bx ]
bx \
bx [
bx Z
bx Y
bx X
bx W
bx V
bx U
xT
xS
xR
xQ
xP
xO
xN
xM
xL
xK
xJ
xI
xH
xG
xF
xE
xD
xC
xB
xA
x@
x?
x>
x=
bx <
bx ;
bx :
bx 9
bx 8
bx 7
bx 6
bx 5
x4
x3
bx 2
bx 1
x0
x/
x.
x-
x,
x+
x*
x)
bx (
x'
bx &
bx %
b100000 $
1#
bx "
0!
$end
#2000
03
1'
b100 <
b0 Z
1/
b0 d
b0 [
b0 e
b0 h
04
b0 \
b0 c
00
b0 U
b0 2
b0 5
b0 k
b0 %
b0 b
b0 1
b0 6
b0 l
0)
0.
0,
0*
0-
0+
0?
0L
0K
0P
0O
0T
0@
0J
0H
0F
0>
0B
0D
0N
0R
0I
0A
0C
b0 Y
0S
0G
0E
0=
0M
0Q
b0 X
b0 V
b0 7
b0 g
b0 8
b0 f
b0 W
b0 9
b0 j
b0 ;
b0 ]
b100 :
b0 &
b0 ^
1!
#3000
b1000011000001000110011 "
b1000011000001000110011 (
0#
#4000
1_
0a
0!
#6000
1!
#8000
1`
0_
0!
#10000
b1000 <
b1000 :
b100 Z
b100 &
b100 ^
1!
#11000
b1000000001000011000001010110011 "
b1000000001000011000001010110011 (
#12000
0`
1a
0!
#14000
0'
b1 [
b1 e
b1 h
b100000000 d
0/
1@
14
b10 \
b10 c
b100 Z
b0 U
b10 2
b10 5
b10 k
b11 %
b11 b
b11 1
b11 6
b11 l
1?
1L
0T
b10000110011 Y
b110011 X
b100000 V
b10 7
b10 g
b11 8
b11 f
b101 9
b101 j
b110011 ;
b1000000001000011000001010110011 ]
1!
#16000
1_
0a
0!
#18000
1!
#19000
b110001010111001100110011 "
b110001010111001100110011 (
#20000
1i
1`
0_
0!
#22000
b1100 <
b1100 :
b1000 Z
b1000 &
b1000 ^
b1 s
1!
#24000
0i
0`
1a
0!
#26000
b1100 \
b1100 c
b1000 [
b1000 e
b1000 h
b1 d
1R
b1100 2
b1100 5
b1100 k
b1010 %
b1010 b
b1010 1
b1010 6
b1010 l
0@
b1110110011 Y
b1110110011 X
b0 V
b1100 7
b1100 g
b1010 8
b1010 f
b111 W
b110 9
b110 j
b110001010111001100110011 ]
1!
#27000
b101000011000001000010011 "
b101000011000001000010011 (
#28000
1_
0a
0!
#30000
1!
#32000
1i
1`
0_
0!
#34000
b10000 <
b1000 t
b10000 :
b1100 Z
b1100 &
b1100 ^
1!
#35000
b111100100100001010010011 "
b111100100100001010010011 (
#36000
0i
0`
1a
0!
#38000
1'
14
b11011 Z
b1111 U
b10000 d
b1011 [
b1011 e
b1011 h
1/
b1111 2
b1111 5
b1111 k
b100 %
b100 b
b100 1
b100 6
b100 l
b1111 \
b1111 c
0L
0R
b1000010011 Y
1=
b1000010011 X
b1111 7
b1111 g
b100 8
b100 f
b100 W
b101 9
b101 j
b10011 ;
b111100100100001010010011 ]
1!
#40000
1_
0a
0!
#42000
1!
#43000
b100001111001100010011 "
b100001111001100010011 (
#44000
1i
1`
0_
0!
#46000
b10100 <
b10100 :
b11111 Z
b10000 &
b10000 ^
b1011 s
1!
#48000
0i
0`
1a
0!
#50000
b1 d
b1 [
b1 e
b1 h
b1 \
b1 c
b1 2
b1 5
b1 k
b1 %
b1 b
b1 1
b1 6
b1 l
b10001 Z
b1 U
b1110010011 Y
0=
1Q
b1110010011 X
b1 7
b1 g
b1 8
b1 f
b111 W
b110 9
b110 j
b100001111001100010011 ]
1!
#52000
1_
0a
0!
#54000
1!
#56000
1i
1`
0_
0!
#58000
b11000 <
b1 t
b11000 :
b10101 Z
b10100 &
b10100 ^
1!
