Laboratorios/Laboratorio 6/mcu.v
module mcu( input clk, //Reloj del microcontrolador
            input rst //Reset del microcontrolador
            );
    
    //Buses con la memoria de programa (IMEM)
    wire [31:0] instr; //Instrucción de entrada
    wire [31:0] iaddr; //Dirección en la IMEM
    
    //Buses con la memoria de datos (DMEM)
    wire [31:0] daddr; //Dirección en la DMEM
    wire [31:0] ddata_in; //Bus de datos DMEM (entrada)
    wire [31:0] ddata_out; //Bus de datos DMEM (salida)
    wire dwr_en; //Señales del bus de control DMEM
    wire drd_en; //
    
    // Instancia del microprocesador RISCV
    my_riscv cpu (
        .rst(rst),
        .clk(clk),
        .instr(instr),
        .iaddr(iaddr),
        .daddr(daddr),
        .ddata_in(ddata_in),
        .ddata_out(ddata_out),
        .dwr_en(dwr_en),
        .drd_en(drd_en)
    );
    
    // Instancia de la memoria de programa
    rom4096x32 IMEM(
        .data(instr),
        .addr(iaddr[13:2])
    );

    sram_4096x32 DMEM(
        .clk(clk),
        .addr(daddr[13:2]),  //Va de [13:2] (12 bits)
        .wr_en(dwr_en),
        .wr_data(ddata_out),
        .rd_en(drd_en),
        .rd_data(ddata_in)
    );

endmodule

//Pon aquí la declaración de la memoria ROM de programa

// --- Declaración de la memoria ROM de programa ---
module rom4096x32 (
    input wire [11:0] addr,  // Dirección (4096 palabras -> 12 bits)
    output reg [31:0] data   // Datos de 32 bits
);

    // Definición del arreglo de memoria (4096 localidades de 32 bits)
    reg [31:0] mem [0:4095];

    // Lógica de lectura combinacional
    always @(*) begin
        data = mem[addr];
    end

    // Inicialización de la memoria usando archivo externo
    initial begin
        // La directiva $readmemh busca un archivo de texto con valores en hexadecimal
        // y los carga secuencialmente en el arreglo 'rom'
        $readmemh("test_program.hex", mem);//se tiene que llamar igual que el archivo que se va a cargar, en este caso programa.hex
        //guía 3 testbench , usar ese
    end
endmodule

module sram_4096x32 (
    input clk,
    input [11:0] addr,        // Dirección interna de 12 bits (para 4096 posiciones)
    input wr_en,              // Habilitación de escritura
    input [31:0] wr_data,     // Bus de datos de entrada (escritura)
    input rd_en,              // Habilitación de lectura
    output [31:0] rd_data     // Bus de datos de salida (lectura)
);

    // Declaración del arreglo de memoria: 4096 posiciones de 32 bits (palabras)
    reg [31:0] ram [0:4095];
    
    // Registro interno para almacenar el dato leído de forma sincrónica
    reg [31:0] data_out_reg;

    // Proceso sincrónico para escritura y lectura
    always @(posedge clk) begin
        // Si la escritura está habilitada, guarda el dato
        if (wr_en) begin
            ram[addr] <= wr_data;
        end
        
        // Lectura sincrónica al registro interno
        data_out_reg <= ram[addr];
    end

    // Lógica de Alta Impedancia (Hi-Z)
    // Cuando rd_en es 0, el bus se libera (pasa a Z) para evitar cortocircuitos
    assign rd_data = (rd_en) ? data_out_reg : 32'bz;
    
endmodule

Laboratorios/Laboratorio 6/alu_riscv.v
module alu_riscv (
    
    input [31:0] a, b,
    input [9:0] ctrl, // Vector de 10 bits: {add, sub, sll, slt, sltu, xor, srl, sra, or, and}
    output reg [31:0] out
);
    wire [4:0] shamt;
    wire [63:0] a_ext;
    wire [31:0] sltu_result;
    wire [31:0] slt_result;
    
    //Valor del shift 
    assign shamt = b[4:0]; 
    //Extensión de signo de la entrada a para 64bits 
    assign a_ext = { {32{a[31]}}, a }; //Valor obtenido por set if less than unsigned (sltu) 
    assign sltu_result = {31'b0, a < b}; //Valor obtenido por set if less than (signed) 
    assign slt_result = (a[31]==b[31]) ? sltu_result : {31'b0, a[31]};
    
    always @(*) begin
     // 
        case (ctrl)
            10'b1000000000: out = a + b;         // add
            10'b0100000000: out = a - b;         // sub
            10'b0010000000: out = a << shamt;   // sll
            10'b0001000000: out = slt_result; // slt
            10'b0000100000: out = sltu_result; // sltu
            10'b0000010000: out = a ^ b;         // xor
            10'b0000001000: out = a >> shamt;   // srl
            10'b0000000100: out = a_ext >> shamt;// SRA , Cambiar este triple >>> , no es compatible, mejor tomar una extension de signo de 64 bits y tomar los bits necesarios dependiendo el valor de corriemiento, según el 
            10'b0000000010: out = a | b;         // or
            10'b0000000001: out = a & b;         // and
            
            default:        out = 32'b0;
        endcase
    end
endmodule

Laboratorios/Laboratorio 5/register_file.v
module register_file (
    input  wire        clk,            // Señal de reloj
    input  wire        wr_en,          // Habilitador de escritura
    input  wire [4:0]  wr_index,       // Dirección de escritura
    input  wire [31:0] wr_data,        // Dato a escribir
    input  wire [4:0]  rd_index1,      // Dirección de lectura 1
    input  wire [4:0]  rd_index2,      // Dirección de lectura 2
    output wire [31:0] rd_data1,       // Dato leído 1
    output wire [31:0] rd_data2        // Dato leído 2
);

    // Memoria de 32 registros de 32 bits
    reg [31:0] mem [31:0];

    integer i;

    // Inicialización opcional (útil para simulación)
    initial begin
        for (i = 0; i < 32; i = i + 1)
            mem[i] = 32'd0;
    end

    // Escritura sincrónica
    always @(posedge clk) begin
        if (wr_en && (wr_index != 5'd0)) begin
            mem[wr_index] <= wr_data;
        end
    end

    // Lecturas combinacionales
    assign rd_data1 = (rd_index1 == 5'd0) ? 32'd0 : mem[rd_index1];
    assign rd_data2 = (rd_index2 == 5'd0) ? 32'd0 : mem[rd_index2];

endmodule

Laboratorios/Laboratorio 6/my_riscv.v
module my_riscv (
    input clk,          // Reloj del procesador
    input rst,          // Reset del procesador
    input [31:0] instr,  // Instrucción de entrada
    output [31:0] iaddr,

    output [31:0] daddr,
    input [31:0] ddata_in,
    output [31:0] ddata_out,
    output dwr_en,
    output drd_en
);

    // Contador de programa
    reg [31:0] pc;
    assign iaddr = pc;  // Conecta el PC al bus de direcciones de la IMEM
    wire [31:0] next_pc;
        

    // Contador en anillo que lleva el registro del estado dentro del ciclo de ejecución
    reg state_fetch, state_decode, state_execute, state_execute2;
    
    always @(negedge clk) begin
        if (rst) begin
            state_fetch <= 1;
            state_decode <= 0;
            state_execute <= 0; 
            state_execute2 <= 0;
        end else begin
            state_fetch <= state_execute2;
            state_decode <= state_fetch;
            state_execute <= state_decode;
            state_execute2 <= state_execute;
        end
    end

    reg [31:0] IR;      // Registro de instrucción
    
    // PC se inicializa en reset; la lógica de avance se agregará más adelante
    always @(posedge clk) begin
        if (rst)
            pc <= 32'h0;
        else if (state_execute)
            pc <= next_pc;
    end

    always @(posedge clk) begin
        if (rst)
            IR <= 32'd0;
        else if (state_fetch)
            IR <= instr;
    end

    // --- Extracción de los campos del registro de instrucción (IR) ---
    wire [6:0] funct7;
    wire [4:0] rs2;
    wire [4:0] rs1;
    wire [2:0] funct3;
    wire [4:0] rd;
    wire [6:0] opcode;

    assign funct7 = IR[31:25];
    assign rs2    = IR[24:20];
    assign rs1    = IR[19:15];
    assign funct3 = IR[14:12];
    assign rd     = IR[11:7];
    assign opcode = IR[6:0];

    // --- Salidas del Register File (RF) ---
    wire [31:0] src1_value;
    wire [31:0] src2_value;

    // --- Operandos de entrada a la ALU ---
    wire [31:0] alu_a;
    wire [31:0] alu_b;

    // --- Salida de la ALU ---
    wire [31:0] alu_out;

    // --- Señales de control de la unidad de control (CU) ---
    wire wr_en;
    wire [10:0] dec_bits;
    wire is_add, is_sub, is_sll, is_slt, is_sltu, is_xor, is_srl, is_sra, is_or, is_and;

    // Tipos de instrucción
    wire is_r_instr;
    wire is_i_instr;
    wire is_s_instr;
    wire is_b_instr;
    wire is_u_instr;
    wire is_j_instr;
    wire is_jal;
    wire is_jalr;
    wire is_load;
    wire is_lb, is_lh, is_lw, is_lbu, is_lhu;
    wire is_valid; //---------------------------------------------------------------------
    reg [31:0] pc_plus_4;
    // señales de salto condicional individuales
    wire is_beq, is_bne, is_blt, is_bge, is_bltu, is_bgeu;
    wire is_auipc, is_lui; // para instrucciones tipo U
   
  register_file rv_rf (
    .clk(clk),
    // solo habilitamos escritura durante el ciclo de ejecución
    .wr_en(wr_en & state_execute2),
    .wr_index(rd),
    //.wr_data(is_load ? ddata_in : alu_out), 
     .wr_data(is_load ? ddata_in : ((is_jal | is_jalr) ? pc_plus_4 : alu_out)), // MUX
    .rd_index1(rs1),
    .rd_data1(src1_value),
    .rd_index2(rs2),
    .rd_data2(src2_value)
 );

    // --- Generación del valor Inmediato (IMM) y extensión de signo ---
    // 
    wire [31:0] imm;
    assign imm = is_i_instr ? { {21{IR[31]}}, IR[30:20] } :
                 is_s_instr ? { {20{IR[31]}}, IR[31:25], IR[11:7] } :
                 is_b_instr ? { {20{IR[31]}}, IR[7], IR[30:25], IR[11:8], 1'b0 } :
                 is_u_instr ? { IR[31:12], 12'b0 } :
                 is_j_instr ? { {12{IR[31]}}, IR[19:12], IR[20], IR[30:21], 1'b0 } :
                 32'b0;

    wire imm_valid = is_i_instr | is_s_instr | is_b_instr | is_u_instr | is_j_instr;
    //wire imm_valid = is_i_instr | is_s_instr | is_b_instr | is_u_instr | is_j_instr | is_jalr;


    // --- comparador para saltos condicionales ---
    // usamos valores firmados para blt/bge, sin signo para bltu/bgeu
    wire taken_br;

    assign taken_br = (is_beq  && (src1_value == src2_value)) |
                      (is_bne  && (src1_value != src2_value)) |
                      (is_blt  && (src1_value < src2_value)) |
                      (is_bge  && (src1_value >= src2_value)) |
                      (is_bltu && (src1_value < src2_value)) |
                      (is_bgeu && (src1_value >= src2_value));

    // Registro que almacena PC+4 en los ciclos fetch/decode

    always @(posedge clk) begin
        if (rst)
            pc_plus_4 <= 32'h0;
        else if (state_fetch)
            pc_plus_4 <= pc + 32'd4;
    end

    // cálculo de valores para siguiente PC
    wire [31:0] br_tgt_pc  = pc + imm;        // PC relativo + immediate
    
    assign next_pc = is_jalr ? alu_out : ((is_j_instr || taken_br) ? br_tgt_pc : pc_plus_4);
    // --- MUX para la entrada B de la ALU ---
    assign alu_a = is_auipc ? pc : is_lui ? 32'b0: src1_value;
    // Aquí ya se implemento la figura 14 del documento de la guía
    assign alu_b = imm_valid ? imm : src2_value; //

    // NUEVO: ASIGNACIONES PARA LA MEMORIA RAM
    // ==========================================
    assign daddr = alu_out;
    assign ddata_out = src2_value;
    assign dwr_en = is_s_instr & (state_execute | state_execute2);
    assign drd_en = is_load & (state_execute | state_execute2);
    

    // --- Instanciación de la ALU ---
    alu_riscv rv_alu (
        .a(alu_a),
        .b(alu_b),
        .out(alu_out),
        // Aquí unimos las señales de tipo R con sus versiones inmediatas (tipo I)
        .ctrl({
            is_add | is_addi | is_lui | is_auipc | is_load | is_s_instr | is_jalr,
            is_sub, 
            is_sll | is_slli, 
            is_slt | is_slti, 
            is_sltu| is_sltui, 
            is_xor | is_xori, 
            is_srl | is_srli, 
            is_sra | is_srai, 
            is_or  | is_ori, 
            is_and | is_andi
        })
    );

    // actualización del PC en etapa execute
    always @(posedge clk) begin
        if (rst) begin
            pc <= 32'h0;
        end else if (state_execute) begin
            pc <= next_pc;
        end
    end

    // --- Unidad de Control (CU) ---
    assign is_valid = (opcode[1:0] == 2'b11);
    
    // Identificación de Tipos
    assign is_r_instr = (opcode[6:2] == 5'b01100);
    assign is_i_instr = (opcode[6:2] == 5'b00000) || (opcode[6:2] == 5'b00100) || (opcode[6:2] == 5'b11001);
    assign is_s_instr = (opcode[6:2] == 5'b01000);
    assign is_b_instr = (opcode[6:2] == 5'b11000);
    assign is_u_instr = (opcode[6:2] == 5'b00101) || (opcode[6:2] == 5'b01101);
    assign is_j_instr = (opcode == 7'b1101111);
    assign is_jal = is_j_instr;
    assign is_jalr = (opcode == 7'b1100111) && (funct3 == 3'b000);

    // Cargas en formato I (LB, LH, LW, LBU, LHU) sobre opcode 0000011
    assign is_lb  = (opcode == 7'b0000011) && (funct3 == 3'b000);
    assign is_lh  = (opcode == 7'b0000011) && (funct3 == 3'b001);
    assign is_lw  = (opcode == 7'b0000011) && (funct3 == 3'b010);
    assign is_lbu = (opcode == 7'b0000011) && (funct3 == 3'b100);
    assign is_lhu = (opcode == 7'b0000011) && (funct3 == 3'b101);

    assign is_load = is_lb | is_lh | is_lw | is_lbu | is_lhu;

    assign wr_en = (is_r_instr | is_i_instr | is_u_instr | is_j_instr | is_load) & is_valid;

    // señales para cada tipo de rama (usar funct3)
    assign is_beq  = is_b_instr && (funct3 == 3'b000);
    assign is_bne  = is_b_instr && (funct3 == 3'b001);
    assign is_blt  = is_b_instr && (funct3 == 3'b100);
    assign is_bge  = is_b_instr && (funct3 == 3'b101);
    assign is_bltu = is_b_instr && (funct3 == 3'b110);
    assign is_bgeu = is_b_instr && (funct3 == 3'b111);

    // Decodificación de instrucciones Tipo R
    assign dec_bits = {funct7[5], funct3, opcode};
    assign is_add  = (dec_bits == 11'b0_000_0110011);
    assign is_sub  = (dec_bits == 11'b1_000_0110011);
    assign is_sll  = (dec_bits == 11'b0_001_0110011);
    assign is_slt  = (dec_bits == 11'b0_010_0110011);
    assign is_sltu = (dec_bits == 11'b0_011_0110011);
    assign is_xor  = (dec_bits == 11'b0_100_0110011);
    assign is_srl  = (dec_bits == 11'b0_101_0110011);
    assign is_sra  = (dec_bits == 11'b1_101_0110011);
    assign is_or   = (dec_bits == 11'b0_110_0110011);
    assign is_and  = (dec_bits == 11'b0_111_0110011);

    // Decodificación de instrucciones Tipo I (Opcodes inmediatos 00100)
    // Para las tipo I, funct7 no existe, solo usamos funct3 y opcode
    wire [9:0] dec_bits_i = {funct3, opcode};
    assign is_addi  = (dec_bits_i == 10'b000_0010011);
    assign is_slti  = (dec_bits_i == 10'b010_0010011);
    assign is_sltui = (dec_bits_i == 10'b011_0010011);
    assign is_xori  = (dec_bits_i == 10'b100_0010011);
    assign is_ori   = (dec_bits_i == 10'b110_0010011);
    assign is_andi  = (dec_bits_i == 10'b111_0010011);
    
    // Casos especiales de tipo I: desplazamientos (usan parte de funct7)
    assign is_slli  = (dec_bits == 11'b0_001_0010011);
    assign is_srli  = (dec_bits == 11'b0_101_0010011);
    assign is_srai  = (dec_bits == 11'b1_101_0010011);

    // Señales tipo U
    assign is_auipc = is_u_instr && (opcode[6:2] == 5'b00101);
    assign is_lui   = is_u_instr && (opcode[6:2] == 5'b01101);

endmodule

Laboratorios/Laboratorio 6/tb_mcu.v
`timescale 1ns/1ps //Test bench para el microcontrolador 
module tb_mcu; 
    // Señales de prueba 
    reg clk; 
    reg rst; 
    
    // Instancia del microcontrolador 
    mcu mcuuq ( 
        .rst(rst), 
        .clk(clk) 
    ); 
    
    integer i; 
    
    // Bloque inicial: aplica estímulos 
    initial begin 
        // Configurar la generación de archivos de volcado 
        $dumpfile("tb_mcu.vcd"); 
        $dumpvars(0, tb_mcu); 
        for(i=0; i<32; i=i+1) 
            $dumpvars(0, mcuuq.cpu.rv_rf.mem[i]); 
        #0; 
        clk = 0; 
        rst = 1; 
        #9; 
        rst = 0; 
        #550; //Termina después de 25 ciclos de reloj 
        #16; // Fin de la simulación 
        $finish; 
    end 
    
    always begin 
        #2 clk=!clk; 
    end 
endmodule

Laboratorios/Laboratorio 6/tb_mcu.vcd
$date
	Thu Mar 26 16:55:38 2026
$end
$version
	Icarus Verilog
$end
$timescale
	1ps
$end
$scope module tb_mcu $end
$var reg 1 ! clk $end
$var reg 1 " rst $end
$var integer 32 # i [31:0] $end
$scope module mcuuq $end
$var wire 1 ! clk $end
$var wire 1 " rst $end
$var wire 32 $ instr [31:0] $end
$var wire 32 % iaddr [31:0] $end
$var wire 1 & dwr_en $end
$var wire 1 ' drd_en $end
$var wire 32 ( ddata_out [31:0] $end
$var wire 32 ) ddata_in [31:0] $end
$var wire 32 * daddr [31:0] $end
$scope module DMEM $end
$var wire 12 + addr [11:0] $end
$var wire 1 ! clk $end
$var wire 1 & wr_en $end
$var wire 32 , wr_data [31:0] $end
$var wire 1 ' rd_en $end
$var wire 32 - rd_data [31:0] $end
$var reg 32 . data_out_reg [31:0] $end
$upscope $end
$scope module IMEM $end
$var wire 12 / addr [11:0] $end
$var reg 32 0 data [31:0] $end
$upscope $end
$scope module cpu $end
$var wire 1 ! clk $end
$var wire 32 1 daddr [31:0] $end
$var wire 32 2 ddata_in [31:0] $end
$var wire 32 3 ddata_out [31:0] $end
$var wire 1 ' drd_en $end
$var wire 1 & dwr_en $end
$var wire 32 4 iaddr [31:0] $end
$var wire 1 5 imm_valid $end
$var wire 32 6 instr [31:0] $end
$var wire 1 7 is_auipc $end
$var wire 1 8 is_beq $end
$var wire 1 9 is_bge $end
$var wire 1 : is_bgeu $end
$var wire 1 ; is_blt $end
$var wire 1 < is_bltu $end
$var wire 1 = is_bne $end
$var wire 1 > is_i_instr $end
$var wire 1 ? is_jal $end
$var wire 1 @ is_jalr $end
$var wire 1 A is_lb $end
$var wire 1 B is_lbu $end
$var wire 1 C is_lh $end
$var wire 1 D is_lhu $end
$var wire 1 E is_load $end
$var wire 1 F is_lui $end
$var wire 1 G is_lw $end
$var wire 1 H is_u_instr $end
$var wire 1 " rst $end
$var wire 1 I taken_br $end
$var wire 1 J wr_en $end
$var wire 32 K src2_value [31:0] $end
$var wire 32 L src1_value [31:0] $end
$var wire 5 M rs2 [4:0] $end
$var wire 5 N rs1 [4:0] $end
$var wire 5 O rd [4:0] $end
$var wire 7 P opcode [6:0] $end
$var wire 32 Q next_pc [31:0] $end
$var wire 1 R is_xori $end
$var wire 1 S is_xor $end
$var wire 1 T is_valid $end
$var wire 1 U is_sub $end
$var wire 1 V is_srli $end
$var wire 1 W is_srl $end
$var wire 1 X is_srai $end
$var wire 1 Y is_sra $end
$var wire 1 Z is_sltui $end
$var wire 1 [ is_sltu $end
$var wire 1 \ is_slti $end
$var wire 1 ] is_slt $end
$var wire 1 ^ is_slli $end
$var wire 1 _ is_sll $end
$var wire 1 ` is_s_instr $end
$var wire 1 a is_r_instr $end
$var wire 1 b is_ori $end
$var wire 1 c is_or $end
$var wire 1 d is_j_instr $end
$var wire 1 e is_b_instr $end
$var wire 1 f is_andi $end
$var wire 1 g is_and $end
$var wire 1 h is_addi $end
$var wire 1 i is_add $end
$var wire 32 j imm [31:0] $end
$var wire 7 k funct7 [6:0] $end
$var wire 3 l funct3 [2:0] $end
$var wire 10 m dec_bits_i [9:0] $end
$var wire 11 n dec_bits [10:0] $end
$var wire 32 o br_tgt_pc [31:0] $end
$var wire 32 p alu_out [31:0] $end
$var wire 32 q alu_b [31:0] $end
$var wire 32 r alu_a [31:0] $end
$var reg 32 s IR [31:0] $end
$var reg 32 t pc [31:0] $end
$var reg 32 u pc_plus_4 [31:0] $end
$var reg 1 v state_decode $end
$var reg 1 w state_execute $end
$var reg 1 x state_execute2 $end
$var reg 1 y state_fetch $end
$scope module rv_alu $end
$var wire 32 z a [31:0] $end
$var wire 32 { b [31:0] $end
$var wire 10 | ctrl [9:0] $end
$var wire 32 } sltu_result [31:0] $end
$var wire 32 ~ slt_result [31:0] $end
$var wire 5 !" shamt [4:0] $end
$var wire 64 "" a_ext [63:0] $end
$var reg 32 #" out [31:0] $end
$upscope $end
$scope module rv_rf $end
$var wire 1 ! clk $end
$var wire 5 $" rd_index1 [4:0] $end
$var wire 5 %" rd_index2 [4:0] $end
$var wire 32 &" wr_data [31:0] $end
$var wire 1 '" wr_en $end
$var wire 5 (" wr_index [4:0] $end
$var wire 32 )" rd_data2 [31:0] $end
$var wire 32 *" rd_data1 [31:0] $end
$var integer 32 +" i [31:0] $end
$upscope $end
$upscope $end
$upscope $end
$upscope $end
$scope module tb_mcu $end
$scope module mcuuq $end
$scope module cpu $end
$scope module rv_rf $end
$var reg 32 ," \mem[0] [31:0] $end
$upscope $end
$upscope $end
$upscope $end
$upscope $end
$scope module tb_mcu $end
$scope module mcuuq $end
$scope module cpu $end
$scope module rv_rf $end
$var reg 32 -" \mem[1] [31:0] $end
$upscope $end
$upscope $end
$upscope $end
$upscope $end
$scope module tb_mcu $end
$scope module mcuuq $end
$scope module cpu $end
$scope module rv_rf $end
$var reg 32 ." \mem[2] [31:0] $end
$upscope $end
$upscope $end
$upscope $end
$upscope $end
$scope module tb_mcu $end
$scope module mcuuq $end
$scope module cpu $end
$scope module rv_rf $end
$var reg 32 /" \mem[3] [31:0] $end
$upscope $end
$upscope $end
$upscope $end
$upscope $end
$scope module tb_mcu $end
$scope module mcuuq $end
$scope module cpu $end
$scope module rv_rf $end
$var reg 32 0" \mem[4] [31:0] $end
$upscope $end
$upscope $end
$upscope $end
$upscope $end
$scope module tb_mcu $end
$scope module mcuuq $end
$scope module cpu $end
$scope module rv_rf $end
$var reg 32 1" \mem[5] [31:0] $end
$upscope $end
$upscope $end
$upscope $end
$upscope $end
$scope module tb_mcu $end
$scope module mcuuq $end
$scope module cpu $end
$scope module rv_rf $end
$var reg 32 2" \mem[6] [31:0] $end
$upscope $end
$upscope $end
$upscope $end
$upscope $end
$scope module tb_mcu $end
$scope module mcuuq $end
$scope module cpu $end
$scope module rv_rf $end
$var reg 32 3" \mem[7] [31:0] $end
$upscope $end
$upscope $end
$upscope $end
$upscope $end
$scope module tb_mcu $end
$scope module mcuuq $end
$scope module cpu $end
$scope module rv_rf $end
$var reg 32 4" \mem[8] [31:0] $end
$upscope $end
$upscope $end
$upscope $end
$upscope $end
$scope module tb_mcu $end
$scope module mcuuq $end
$scope module cpu $end
$scope module rv_rf $end
$var reg 32 5" \mem[9] [31:0] $end
$upscope $end
$upscope $end
$upscope $end
$upscope $end
$scope module tb_mcu $end
$scope module mcuuq $end
$scope module cpu $end
$scope module rv_rf $end
$var reg 32 6" \mem[10] [31:0] $end
$upscope $end
$upscope $end
$upscope $end
$upscope $end
$scope module tb_mcu $end
$scope module mcuuq $end
$scope module cpu $end
$scope module rv_rf $end
$var reg 32 7" \mem[11] [31:0] $end
$upscope $end
$upscope $end
$upscope $end
$upscope $end
$scope module tb_mcu $end
$scope module mcuuq $end
$scope module cpu $end
$scope module rv_rf $end
$var reg 32 8" \mem[12] [31:0] $end
$upscope $end
$upscope $end
$upscope $end
$upscope $end
$scope module tb_mcu $end
$scope module mcuuq $end
$scope module cpu $end
$scope module rv_rf $end
$var reg 32 9" \mem[13] [31:0] $end
$upscope $end
$upscope $end
$upscope $end
$upscope $end
$scope module tb_mcu $end
$scope module mcuuq $end
$scope module cpu $end
$scope module rv_rf $end
$var reg 32 :" \mem[14] [31:0] $end
$upscope $end
$upscope $end
$upscope $end
$upscope $end
$scope module tb_mcu $end
$scope module mcuuq $end
$scope module cpu $end
$scope module rv_rf $end
$var reg 32 ;" \mem[15] [31:0] $end
$upscope $end
$upscope $end
$upscope $end
$upscope $end
$scope module tb_mcu $end
$scope module mcuuq $end
$scope module cpu $end
$scope module rv_rf $end
$var reg 32 <" \mem[16] [31:0] $end
$upscope $end
$upscope $end
$upscope $end
$upscope $end
$scope module tb_mcu $end
$scope module mcuuq $end
$scope module cpu $end
$scope module rv_rf $end
$var reg 32 =" \mem[17] [31:0] $end
$upscope $end
$upscope $end
$upscope $end
$upscope $end
$scope module tb_mcu $end
$scope module mcuuq $end
$scope module cpu $end
$scope module rv_rf $end
$var reg 32 >" \mem[18] [31:0] $end
$upscope $end
$upscope $end
$upscope $end
$upscope $end
$scope module tb_mcu $end
$scope module mcuuq $end
$scope module cpu $end
$scope module rv_rf $end
$var reg 32 ?" \mem[19] [31:0] $end
$upscope $end
$upscope $end
$upscope $end
$upscope $end
$scope module tb_mcu $end
$scope module mcuuq $end
$scope module cpu $end
$scope module rv_rf $end
$var reg 32 @" \mem[20] [31:0] $end
$upscope $end
$upscope $end
$upscope $end
$upscope $end
$scope module tb_mcu $end
$scope module mcuuq $end
$scope module cpu $end
$scope module rv_rf $end
$var reg 32 A" \mem[21] [31:0] $end
$upscope $end
$upscope $end
$upscope $end
$upscope $end
$scope module tb_mcu $end
$scope module mcuuq $end
$scope module cpu $end
$scope module rv_rf $end
$var reg 32 B" \mem[22] [31:0] $end
$upscope $end
$upscope $end
$upscope $end
$upscope $end
$scope module tb_mcu $end
$scope module mcuuq $end
$scope module cpu $end
$scope module rv_rf $end
$var reg 32 C" \mem[23] [31:0] $end
$upscope $end
$upscope $end
$upscope $end
$upscope $end
$scope module tb_mcu $end
$scope module mcuuq $end
$scope module cpu $end
$scope module rv_rf $end
$var reg 32 D" \mem[24] [31:0] $end
$upscope $end
$upscope $end
$upscope $end
$upscope $end
$scope module tb_mcu $end
$scope module mcuuq $end
$scope module cpu $end
$scope module rv_rf $end
$var reg 32 E" \mem[25] [31:0] $end
$upscope $end
$upscope $end
$upscope $end
$upscope $end
$scope module tb_mcu $end
$scope module mcuuq $end
$scope module cpu $end
$scope module rv_rf $end
$var reg 32 F" \mem[26] [31:0] $end
$upscope $end
$upscope $end
$upscope $end
$upscope $end
$scope module tb_mcu $end
$scope module mcuuq $end
$scope module cpu $end
$scope module rv_rf $end
$var reg 32 G" \mem[27] [31:0] $end
$upscope $end
$upscope $end
$upscope $end
$upscope $end
$scope module tb_mcu $end
$scope module mcuuq $end
$scope module cpu $end
$scope module rv_rf $end
$var reg 32 H" \mem[28] [31:0] $end
$upscope $end
$upscope $end
$upscope $end
$upscope $end
$scope module tb_mcu $end
$scope module mcuuq $end
$scope module cpu $end
$scope module rv_rf $end
$var reg 32 I" \mem[29] [31:0] $end
$upscope $end
$upscope $end
$upscope $end
$upscope $end
$scope module tb_mcu $end
$scope module mcuuq $end
$scope module cpu $end
$scope module rv_rf $end
$var reg 32 J" \mem[30] [31:0] $end
$upscope $end
$upscope $end
$upscope $end
$upscope $end
$scope module tb_mcu $end
$scope module mcuuq $end
$scope module cpu $end
$scope module rv_rf $end
$var reg 32 K" \mem[31] [31:0] $end
$upscope $end
$upscope $end
$upscope $end
$upscope $end
$enddefinitions $end
$comment Show the parameter values. $end
$dumpall
$end
#0
$dumpvars
b0 K"
b0 J"
b0 I"
b0 H"
b0 G"
b0 F"
b0 E"
b0 D"
b0 C"
b0 B"
b0 A"
b0 @"
b0 ?"
b0 >"
b0 ="
b0 <"
b0 ;"
b0 :"
b0 9"
b0 8"
b0 7"
b0 6"
b0 5"
b0 4"
b0 3"
b0 2"
b0 1"
b0 0"
b0 /"
b0 ."
b0 -"
b0 ,"
b100000 +"
bx *"
bx )"
bx ("
0'"
bx &"
bx %"
bx $"
b0 #"
bx ""
bx !"
b0x ~
b0x }
bx |
bx {
bx z
1y
0x
0w
0v
bx u
bx t
bx s
bx r
bx q
b0 p
bx o
bx n
bx m
bx l
bx k
bx j
xi
xh
xg
xf
xe
xd
xc
xb
xa
x`
x_
x^
x]
x\
x[
xZ
xY
xX
xW
xV
xU
xT
xS
xR
bx Q
bx P
bx O
bx N
bx M
bx L
bx K
xJ
xI
xH
xG
xF
xE
xD
xC
xB
xA
x@
x?
x>
x=
x<
x;
x:
x9
x8
x7
bx 6
x5
bx 4
bx 3
bz 2
b0 1
bx 0
bx /
bx .
bz -
bx ,
b0 +
b0 *
bz )
bx (
0'
0&
bx %
bx $
b100000 #
1"
0!
$end
#2000
0I
15
b0 ~
b0 Q
b0 }
b0 &"
0E
b0 o
b0 ""
b0 !"
1>
b0 |
b0 r
b0 z
b0 q
b0 {
0J
0H
07
0F
b0 j
b0 (
b0 ,
b0 3
b0 K
b0 )"
b0 L
b0 *"
08
0=
0;
09
0<
0:
0T
0a
0`
0e
0@
0A
0C
0G
0B
0D
0i
0U
0_
0]
0[
0S
0W
0Y
0c
0g
0^
0V
0X
b0 n
0h
0\
0Z
0R
0b
0f
b0 m
b110000000000010100010011 $
b110000000000010100010011 0
b110000000000010100010011 6
b0 k
b0 M
b0 %"
b0 N
b0 $"
b0 l
b0 O
b0 ("
0?
0d
b0 P
b0 /
b0 s
b0 u
b0 %
b0 4
b0 t
1!
#4000
0!
#6000
1!
#8000
0!
#9000
0"
#10000
b1100 &"
b11 +
b1100 *
b1100 1
b1100 p
b1100 #"
b1000000000 |
b1 ~
b1100 !"
b1 }
b1100 q
b1100 {
1J
b1100 o
b1100 j
1T
b10011 n
1h
b10011 m
b100 Q
b1100 M
b1100 %"
b1010 O
b1010 ("
b10011 P
b110000000000010100010011 s
b100 u
1!
#12000
1v
0y
0!
#14000
1!
#16000
1w
0v
0!
#18000
b1100000000010110010011 $
b1100000000010110010011 0
b1100000000010110010011 6
b1 /
b10000 o
b100 %
b100 4
b100 t
1!
#20000
1'"
1x
0w
0!
#22000
b1100 6"
1!
#24000
0'"
0x
1y
0!
#26000
b11 &"
b0 +
b11 *
b11 1
b11 p
b11 #"
b11 !"
b11 q
b11 {
b111 o
b11 j
b1000 Q
b11 M
b11 %"
b1011 O
b1011 ("
b1100000000010110010011 s
b1000 u
1!
#28000
1v
0y
0!
#30000
1!
#32000
1w
0v
0!
#34000
b100000000000000011101111 $
b100000000000000011101111 0
b100000000000000011101111 6
b10 /
b1011 o
b1000 %
b1000 4
b1000 t
1!
#36000
1'"
1x
0w
0!
#38000
b11 7"
1!
#40000
0'"
0x
1y
0!
#42000
b0 |
b0 +
b0 *
b0 1
b0 p
b0 #"
b1000 !"
0>
b1100 &"
b1000 q
b1000 {
b10000 o
b1000 j
b1101111 n
0h
b1101111 m
b10000 Q
b1000 M
b1000 %"
b1 O
b1 ("
1?
1d
b1101111 P
b100000000000000011101111 s
b1100 u
1!
#44000
1v
0y
0!
#46000
1!
#48000
1w
0v
0!
#50000
b11000 Q
b101101010000010100110011 $
b101101010000010100110011 0
b101101010000010100110011 6
b100 /
b11000 o
b10000 %
b10000 4
b10000 t
1!
#52000
1'"
1x
0w
0!
#54000
b1100 -"
1!
#56000
0'"
0x
1y
0!
